radar_mapping_api/__init__.py
radar_mapping_api/client.py
radar_mapping_api/helpers.py
radar_mapping_api/models.py
radar_mapping_api-0.1.0.dist-info/WHEEL
radar_mapping_api-0.1.0.dist-info/METADATA
radar_mapping_api-0.1.0.dist-info/RECORD
