Metadata-Version: 2.3
Name: radar-mapping-api
Version: 0.1.0
Summary: A Python client for the Radar.io geocoding, mapping, and geolocation API
Keywords: radar,radar.io,geocoding,geolocation,mapping,reverse-geocoding,places,api-client
Author: Michael Bianco
Author-email: Michael Bianco <mike@mikebian.co>
Requires-Dist: httpx>=0.28.1
Requires-Dist: pydantic>=2.12.3
Requires-Dist: tenacity>=9.1.2
Requires-Dist: sentry-sdk>=2.0.0 ; extra == 'sentry'
Requires-Python: >=3.10
Project-URL: Repository, https://github.com/iloveitaly/radar-mapping-api
Provides-Extra: sentry
